hipcall_sdk/__init__.py
hipcall_sdk/client/__init__.py
hipcall_sdk/client/async_client.py
hipcall_sdk/client/base.py
hipcall_sdk/client/client.py
hipcall_sdk/constants.py
hipcall_sdk/exceptions.py
hipcall_sdk/models.py
hipcall_sdk-0.1.2.dist-info/LICENSE
hipcall_sdk-0.1.2.dist-info/METADATA
hipcall_sdk-0.1.2.dist-info/WHEEL
hipcall_sdk-0.1.2.dist-info/RECORD
