Metadata-Version: 2.1
Name: hipcall-sdk
Version: 0.1.2
Summary: Official Hipcall API Wrapper written in Python
Home-page: https://github.com/hipcall/python_sdk
License: MIT
Keywords: hipcall,sdk,api
Author: Ahmet Sezgin Duran
Author-email: sezgin.duran@linux.org.tr
Requires-Python: >=3.12,<4.0
Classifier: License :: OSI Approved :: MIT License
Classifier: Programming Language :: Python :: 3
Classifier: Programming Language :: Python :: 3.12
Requires-Dist: aiohttp (>=3.10.9,<4.0.0)
Requires-Dist: pydantic (>=2.9.2,<3.0.0)
Requires-Dist: requests (>=2.32.3,<3.0.0)
Project-URL: Repository, https://github.com/hipcall/python_sdk
